libs/logging/.flake8
libs/logging/.gitignore
libs/logging/README.md
libs/logging/harken/logging/__init__.py
libs/logging/harken/logging/configure.py
libs/logging/pyproject.toml
libs/logging/tests/__init__.py
libs/translation/.flake8
libs/translation/.gitignore
libs/translation/README.md
libs/translation/harken/translation/__init__.py
libs/translation/harken/translation/data/deepl_languages.json
libs/translation/harken/translation/data/general_languages.json
libs/translation/harken/translation/data/google_languages.json
libs/translation/harken/translation/engines.py
libs/translation/harken/translation/languages.py
libs/translation/pyproject.toml
libs/translation/tests/__init__.py
harken-0.0.1.1.dist-info/LICENSE
harken-0.0.1.1.dist-info/METADATA
harken-0.0.1.1.dist-info/WHEEL
harken-0.0.1.1.dist-info/RECORD
