Metadata-Version: 2.1
Name: harken
Version: 0.0.1.1
Summary: A library with utilities
Author: Juan Luis Garciaa
Author-email: juanluis1702@gmail.com
Requires-Python: >=3.8
Classifier: Programming Language :: Python :: 3
Classifier: Programming Language :: Python :: 3.8
Classifier: Programming Language :: Python :: 3.9
Classifier: Programming Language :: Python :: 3.10
Classifier: Programming Language :: Python :: 3.11
Classifier: Programming Language :: Python :: 3.12
